Metadata-Version: 1.1
Name: static-variables
Version: 0.0.5
Summary: Static variables for Python
Home-page: https://github.com/MitalAshok/static_variables
Author: Mital Ashok
Author-email: mital.vaja@googlemail.com
License: MIT
Keywords: library,static,CPython,code object
Platform: any
Classifier: Development Status :: 3 - Alpha
Classifier: Intended Audience :: Developers
Classifier: License :: OSI Approved :: MIT License
Classifier: Operating System :: OS Independent
Classifier: Programming Language :: Python :: 3
Classifier: Programming Language :: Python :: 3.6
Classifier: Programming Language :: Python :: Implementation :: CPython
Classifier: Topic :: Software Development :: Libraries
